smolhub/__init__.py
smolhub/helper/__init__.py
smolhub/helper/count_parameters.py
smolhub/helper/print_model_details.py
smolhub/helper/save_model.py
smolhub/helper/scheduler.py
smolhub/helper/visualize.py
smolhub/helper/dataset/__init__.py
smolhub/helper/dataset/dataset_main.py
smolhub/helper/dataset/load_config.py
smolhub/helper/dataset/prepare_dataset.py
smolhub/helper/dataset/prepare_dataset_preference_alignment.py
smolhub/helper/dataset/prepare_dataset_pretrain.py
smolhub/scripts/__init__.py
smolhub/scripts/dora.py
smolhub/scripts/finetune.py
smolhub/scripts/lora.py
smolhub/scripts/preference.py
smolhub/scripts/pretrain.py
smolhub-0.6.8.dist-info/METADATA
smolhub-0.6.8.dist-info/WHEEL
smolhub-0.6.8.dist-info/top_level.txt
smolhub-0.6.8.dist-info/RECORD
