Metadata-Version: 2.4
Name: smolhub
Version: 0.6.8
Author: Yuvraj Singh
Author-email: yuvraj.mist@gmail.com
Requires-Python: >=3.8
Requires-Dist: torch
Requires-Dist: transformers
Requires-Dist: datasets
Requires-Dist: wandb
Requires-Dist: tqdm
Requires-Dist: pyyaml
Requires-Dist: numpy
Dynamic: author
Dynamic: author-email
Dynamic: description
Dynamic: description-content-type
Dynamic: requires-dist
Dynamic: requires-python
